think_captcha/__init__.py
think_captcha/think_captcha.py
think_captcha-0.2.2.dist-info/LICENCE.txt
think_captcha-0.2.2.dist-info/METADATA
think_captcha-0.2.2.dist-info/WHEEL
think_captcha-0.2.2.dist-info/top_level.txt
think_captcha-0.2.2.dist-info/RECORD
